muratin_hesap_makinasi/__init__.py
muratin_hesap_makinasi/__main__.py
muratin_hesap_makinasi/hesap_makinasi.py
muratin_hesap_makinasi-2.0.0.dist-info/LICENSE
muratin_hesap_makinasi-2.0.0.dist-info/METADATA
muratin_hesap_makinasi-2.0.0.dist-info/WHEEL
muratin_hesap_makinasi-2.0.0.dist-info/entry_points.txt
muratin_hesap_makinasi-2.0.0.dist-info/top_level.txt
muratin_hesap_makinasi-2.0.0.dist-info/RECORD
