Metadata-Version: 2.1
Name: muratin-hesap-makinasi
Version: 2.0.0
Summary: muratin hesap makinasi
Home-page: https://github.com/muratcabuk/muratin-hesap-makinasi
Author: murat cabuk
Author-email: mcabuk@gmail.com
License: MIT
Platform: UNKNOWN
Classifier: Programming Language :: Python :: 3
Classifier: Programming Language :: Python :: 3.4
Classifier: Programming Language :: Python :: 3.5
Classifier: Programming Language :: Python :: 3.6
Classifier: License :: OSI Approved :: MIT License
Classifier: Programming Language :: Python :: 3.7
Requires-Python: >=3.0
Requires-Dist: click (>=8.0.0)
Requires-Dist: requests (>=2.0.0)
